<?1.0?>
<userDefaultRoot>
    <aa>0</aa>
    <l0>6</l0>
    <l1>9</l1>
    <a>14284</a>
    <b>60</b>
    <c>10</c>
    <d>1</d>
    <e>3</e>
    <o0>55</o0>
    <j0>0</j0>
    <k0>0</k0>
    <i0>0</i0>
    <i1>0</i1>
    <i2>100</i2>
    <i3>5</i3>
    <i4>0</i4>
    <i5>0</i5>
    <i6>0</i6>
    <i7>0</i7>
    <i8>0</i8>
    <i9>402</i9>
    <i10>0</i10>
    <i11>0</i11>
    <i12>0</i12>
    <i13>0</i13>
    <i14>0</i14>
    <i15>0</i15>
    <i16>0</i16>
    <i17>0</i17>
    <z>620</z>
    <ba>3</ba>
    <bb>6</bb>
    <bc0>0</bc0>
    <bc1>0</bc1>
    <bc2>0</bc2>
    <bc3>0</bc3>
    <bc4>0</bc4>
    <bc5>0</bc5>
    <_s1>1</_s1>
    <_s2>0</_s2>
    <g0>1</g0>
    <g1>1</g1>
    <h0>2</h0>
    <v0>0</v0>
    <w0>0</w0>
    <x0>0</x0>
    <bd0>0</bd0>
    <be0>0</be0>
    <name>NP0000</name>
    <_f>1</_f>
    <p>184</p>
    <q>1</q>
    <r>9</r>
    <s0>1</s0>
    <s1>19</s1>
    <s2>9</s2>
    <s3>2</s3>
    <s4>22</s4>
    <s5>14</s5>
    <s6>6</s6>
    <s7>30</s7>
    <s8>27</s8>
    <s9>32</s9>
    <t>1</t>
    <u>2</u>
    <j2>0</j2>
    <k2>1</k2>
    <j3>0</j3>
    <k3>1</k3>
    <_a>126</_a>
    <_b>1</_b>
    <_c>9</_c>
    <_d>5</_d>
    <y0>12</y0>
    <y1>0</y1>
    <y2>0</y2>
    <y3>0</y3>
    <j14>0</j14>
    <k14>0</k14>
    <j17>0</j17>
    <k17>0</k17>
    <g31>0</g31>
    <h30>0</h30>
    <v30>0</v30>
    <w30>0</w30>
    <x30>0</x30>
    <bd30>0</bd30>
    <be30>0</be30>
    <g2>1</g2>
    <g3>1</g3>
    <g4>1</g4>
    <g5>1</g5>
    <g6>1</g6>
    <g7>0</g7>
    <g8>0</g8>
    <g9>0</g9>
    <g10>0</g10>
    <g11>0</g11>
    <g12>0</g12>
    <g13>0</g13>
    <g14>0</g14>
    <g15>0</g15>
    <g16>0</g16>
    <g17>0</g17>
    <g18>0</g18>
    <g19>0</g19>
    <g20>0</g20>
    <g21>0</g21>
    <g22>0</g22>
    <g23>0</g23>
    <g24>0</g24>
    <g25>0</g25>
    <g26>0</g26>
    <g27>0</g27>
    <g28>0</g28>
    <g29>0</g29>
    <g30>0</g30>
    <g32>0</g32>
    <g33>0</g33>
    <g34>0</g34>
    <g35>0</g35>
    <h1>1</h1>
    <h2>2</h2>
    <h3>1</h3>
    <h4>1</h4>
    <h5>0</h5>
    <h6>0</h6>
    <h7>0</h7>
    <h8>0</h8>
    <h9>0</h9>
    <h10>0</h10>
    <h11>0</h11>
    <h12>0</h12>
    <h13>0</h13>
    <h14>0</h14>
    <h15>0</h15>
    <h16>0</h16>
    <h17>0</h17>
    <h18>0</h18>
    <h19>0</h19>
    <h20>0</h20>
    <h21>0</h21>
    <h22>0</h22>
    <h23>0</h23>
    <h24>0</h24>
    <h25>0</h25>
    <h26>0</h26>
    <h27>0</h27>
    <h28>0</h28>
    <h29>0</h29>
    <h31>0</h31>
    <h32>0</h32>
    <h33>0</h33>
    <h34>0</h34>
    <h35>0</h35>
    <j1>0</j1>
    <j4>0</j4>
    <j5>0</j5>
    <j6>0</j6>
    <j7>0</j7>
    <j8>0</j8>
    <j9>0</j9>
    <j10>0</j10>
    <j11>0</j11>
    <j12>0</j12>
    <j13>0</j13>
    <j15>0</j15>
    <j16>0</j16>
    <k1>0</k1>
    <k4>0</k4>
    <k5>0</k5>
    <k6>1</k6>
    <k7>0</k7>
    <k8>0</k8>
    <k9>1</k9>
    <k10>0</k10>
    <k11>0</k11>
    <k12>0</k12>
    <k13>0</k13>
    <k15>0</k15>
    <k16>0</k16>
    <l2>-1</l2>
    <m0>0</m0>
    <m1>0</m1>
    <m2>0</m2>
    <m3>0</m3>
    <m4>0</m4>
    <m5>0</m5>
    <m6>0</m6>
    <m7>0</m7>
    <m8>0</m8>
    <m9>0</m9>
    <m10>0</m10>
    <m11>0</m11>
    <m12>0</m12>
    <m13>0</m13>
    <m14>0</m14>
    <m15>0</m15>
    <m16>0</m16>
    <m17>0</m17>
    <m18>0</m18>
    <m19>0</m19>
    <m20>0</m20>
    <m21>0</m21>
    <m22>0</m22>
    <m23>0</m23>
    <m24>0</m24>
    <m25>0</m25>
    <m26>0</m26>
    <m27>0</m27>
    <m28>0</m28>
    <m29>0</m29>
    <m30>0</m30>
    <m31>0</m31>
    <m32>0</m32>
    <m33>0</m33>
    <m34>0</m34>
    <m35>0</m35>
    <m36>0</m36>
    <m37>0</m37>
    <m38>0</m38>
    <m39>0</m39>
    <m40>0</m40>
    <m41>0</m41>
    <m42>0</m42>
    <m43>0</m43>
    <m44>0</m44>
    <m45>0</m45>
    <m46>0</m46>
    <m47>0</m47>
    <m48>0</m48>
    <m49>0</m49>
    <m50>0</m50>
    <m51>0</m51>
    <m52>0</m52>
    <m53>0</m53>
    <m54>0</m54>
    <m55>0</m55>
    <m56>0</m56>
    <m57>0</m57>
    <m58>0</m58>
    <m59>0</m59>
    <m60>0</m60>
    <m61>0</m61>
    <m62>0</m62>
    <n0>10</n0>
    <n1>33</n1>
    <n2>33</n2>
    <n3>33</n3>
    <n4>50</n4>
    <n5>392</n5>
    <n6>392</n6>
    <n7>392</n7>
    <n8>10</n8>
    <n9>45</n9>
    <n10>45</n10>
    <n11>45</n11>
    <n12>0</n12>
    <n13>0</n13>
    <n14>0</n14>
    <n15>0</n15>
    <n16>0</n16>
    <n17>0</n17>
    <n18>0</n18>
    <n19>0</n19>
    <n20>0</n20>
    <n21>0</n21>
    <n22>0</n22>
    <n23>0</n23>
    <n24>0</n24>
    <n25>0</n25>
    <n26>0</n26>
    <n27>0</n27>
    <n28>0</n28>
    <n29>0</n29>
    <n30>0</n30>
    <n31>0</n31>
    <n32>0</n32>
    <n33>0</n33>
    <n34>0</n34>
    <n35>0</n35>
    <n36>0</n36>
    <n37>0</n37>
    <n38>0</n38>
    <n39>0</n39>
    <n40>1</n40>
    <n41>1</n41>
    <n42>1</n42>
    <n43>1</n43>
    <n44>0</n44>
    <n45>0</n45>
    <n46>0</n46>
    <n47>0</n47>
    <n48>0</n48>
    <n49>0</n49>
    <n50>0</n50>
    <n51>0</n51>
    <n52>0</n52>
    <n53>0</n53>
    <n54>0</n54>
    <n55>3</n55>
    <n56>5</n56>
    <n57>5</n57>
    <n58>5</n58>
    <n59>0</n59>
    <n60>0</n60>
    <n61>0</n61>
    <n62>0</n62>
    <o1>0</o1>
    <v1>0</v1>
    <v2>0</v2>
    <v3>0</v3>
    <v4>0</v4>
    <v5>0</v5>
    <v6>0</v6>
    <v7>0</v7>
    <v8>0</v8>
    <v9>0</v9>
    <v10>0</v10>
    <v11>0</v11>
    <v12>0</v12>
    <v13>0</v13>
    <v14>0</v14>
    <v15>0</v15>
    <v16>0</v16>
    <v17>0</v17>
    <w1>0</w1>
    <w2>0</w2>
    <w3>0</w3>
    <w4>0</w4>
    <w5>0</w5>
    <w6>0</w6>
    <w7>0</w7>
    <w8>0</w8>
    <w9>0</w9>
    <w10>0</w10>
    <w11>0</w11>
    <w12>0</w12>
    <w13>0</w13>
    <w14>0</w14>
    <w15>0</w15>
    <w16>0</w16>
    <w17>0</w17>
    <x1>0</x1>
    <x2>0</x2>
    <x3>0</x3>
    <x4>0</x4>
    <x5>0</x5>
    <x6>0</x6>
    <x7>0</x7>
    <x8>0</x8>
    <x9>0</x9>
    <x10>0</x10>
    <x11>0</x11>
    <x12>0</x12>
    <x13>0</x13>
    <x14>0</x14>
    <x15>0</x15>
    <x16>0</x16>
    <x17>0</x17>
    <_g>0</_g>
    <bd1>0</bd1>
    <bd2>0</bd2>
    <bd3>0</bd3>
    <bd4>0</bd4>
    <bd5>0</bd5>
    <bd6>0</bd6>
    <bd7>0</bd7>
    <bd8>0</bd8>
    <bd9>0</bd9>
    <bd10>0</bd10>
    <bd11>0</bd11>
    <bd12>0</bd12>
    <bd13>0</bd13>
    <bd14>0</bd14>
    <bd15>0</bd15>
    <bd16>0</bd16>
    <bd17>0</bd17>
    <be1>0</be1>
    <be2>0</be2>
    <be3>0</be3>
    <be4>0</be4>
    <be5>0</be5>
    <be6>0</be6>
    <be7>0</be7>
    <be8>0</be8>
    <be9>0</be9>
    <be10>0</be10>
    <be11>0</be11>
    <be12>0</be12>
    <be13>0</be13>
    <be14>0</be14>
    <be15>0</be15>
    <be16>0</be16>
    <be17>0</be17>
    <f>5</f>
</userDefaultRoot>
